[{"name":"Adrian Macdonald","sex":"M","age":33,"bib":"1","hometown":"Fort Collins, CO, USA","rank":1,"gender_rank":1,"division_rank":1,"pace":"09:37","time":"16:05:44"},{"name":"JP Giblin","sex":"M","age":28,"bib":"142","hometown":"Boulder, CO, USA","rank":2,"gender_rank":2,"division_rank":2,"pace":"10:50","time":"18:07:50"},{"name":"Ryan Kaiser","sex":"M","age":43,"bib":"280","hometown":"Bend, OR, USA","rank":3,"gender_rank":3,"division_rank":3,"pace":"10:58","time":"18:21:21"},{"name":"Tyler Andrews","sex":"M","age":32,"bib":"16","hometown":"Concord, MA, USA","rank":4,"gender_rank":4,"division_rank":1,"pace":"11:09","time":"18:40:04"},{"name":"Christopher Harrington","sex":"M","age":38,"bib":"10","hometown":"Golden, CO, USA","rank":5,"gender_rank":5,"division_rank":2,"pace":"11:12","time":"18:45:08"},{"name":"Devon Colegrove","sex":"M","age":27,"bib":"431","hometown":"Loveland, CO, USA","rank":6,"gender_rank":6,"division_rank":1,"pace":"11:24","time":"19:03:48"},{"name":"Joel Anderson","sex":"M","age":40,"bib":"346","hometown":"Leadville, CO, USA","rank":7,"gender_rank":7,"division_rank":1,"pace":"11:27","time":"19:10:12"},{"name":"Joshua Eberly","sex":"M","age":41,"bib":"470","hometown":"Gunnison, CO, USA","rank":8,"gender_rank":8,"division_rank":2,"pace":"11:36","time":"19:24:41"},{"name":"BRIAN M BABYAK","sex":"M","age":25,"bib":"634","hometown":"Albuquerque, NM, USA","rank":9,"gender_rank":9,"division_rank":2,"pace":"11:37","time":"19:25:58"},{"name":"Guillaume Perrot","sex":"M","age":31,"bib":"739","hometown":"Hong Kong, -, HKG","rank":10,"gender_rank":10,"division_rank":3,"pace":"11:39","time":"19:29:47"},{"name":"Marvin Sandoval","sex":"M","age":44,"bib":"101","hometown":"Leadville, CO, USA","rank":11,"gender_rank":11,"division_rank":3,"pace":"11:41","time":"19:32:43"},{"name":"Clare Gallagher","sex":"F","age":30,"bib":"9","hometown":"Boulder, CO, USA","rank":12,"gender_rank":1,"division_rank":1,"pace":"11:44","time":"19:37:57"},{"name":"Todd Dill","sex":"M","age":40,"bib":"460","hometown":"Castle Rock, CO, USA","rank":13,"gender_rank":12,"division_rank":4,"pace":"11:50","time":"19:47:41"},{"name":"Matthew Vira","sex":"M","age":23,"bib":"897","hometown":"Louisville, CO, USA","rank":14,"gender_rank":13,"division_rank":3,"pace":"12:05","time":"20:13:21"},{"name":"Devin Vennard","sex":"M","age":29,"bib":"894","hometown":"Leadville, CO, USA","rank":15,"gender_rank":14,"division_rank":4,"pace":"12:12","time":"20:24:28"},{"name":"Fan Zhou","sex":"M","age":34,"bib":"253","hometown":"Seattle, WA, USA","rank":16,"gender_rank":15,"division_rank":4,"pace":"12:27","time":"20:50:32"},{"name":"Duncan Callahan","sex":"M","age":39,"bib":"17","hometown":"Gunnison, CO, USA","rank":17,"gender_rank":16,"division_rank":5,"pace":"12:30","time":"20:54:32"},{"name":"Rodrigo Jimenez","sex":"M","age":46,"bib":"6","hometown":"Leadville, CO, USA","rank":18,"gender_rank":17,"division_rank":5,"pace":"12:34","time":"21:02:22"},{"name":"Michael Martinez","sex":"M","age":36,"bib":"650","hometown":"Colorado Springs, CO, USA","rank":19,"gender_rank":18,"division_rank":6,"pace":"12:41","time":"21:14:11"},{"name":"Martin Malherbe","sex":"M","age":46,"bib":"643","hometown":"Sandton, -, ZAF","rank":20,"gender_rank":19,"division_rank":6,"pace":"12:43","time":"21:17:28"},{"name":"Patrick Cade","sex":"M","age":38,"bib":"414","hometown":"Leadville, CO, USA","rank":21,"gender_rank":20,"division_rank":7,"pace":"12:45","time":"21:19:29"},{"name":"Zachary Russell","sex":"M","age":29,"bib":"790","hometown":"Basalt, CO, USA","rank":22,"gender_rank":21,"division_rank":5,"pace":"12:48","time":"21:25:46"},{"name":"Fabio Di Giacomo","sex":"M","age":43,"bib":"459","hometown":"Castronno, -, ITA","rank":23,"gender_rank":22,"division_rank":7,"pace":"12:54","time":"21:35:16"},{"name":"Cory Logsdon","sex":"M","age":34,"bib":"625","hometown":"Omaha, NE, USA","rank":24,"gender_rank":23,"division_rank":8,"pace":"12:57","time":"21:39:37"},{"name":"Alisyn Hummelberg","sex":"F","age":30,"bib":"559","hometown":"Estes Park, CO, USA","rank":25,"gender_rank":2,"division_rank":1,"pace":"13:08","time":"21:58:59"},{"name":"Chad Lasater","sex":"M","age":50,"bib":"607","hometown":"Sugar Land, TX, USA","rank":26,"gender_rank":24,"division_rank":1,"pace":"13:17","time":"22:13:14"},{"name":"Max Robinson","sex":"M","age":29,"bib":"774","hometown":"Fruita, CO, USA","rank":27,"gender_rank":25,"division_rank":6,"pace":"13:18","time":"22:15:55"},{"name":"Daniel Harper","sex":"M","age":40,"bib":"104","hometown":"Phoenix, AZ, USA","rank":28,"gender_rank":26,"division_rank":8,"pace":"13:19","time":"22:16:48"},{"name":"Ryan Simmons","sex":"M","age":34,"bib":"817","hometown":"Edwards, CO, USA","rank":29,"gender_rank":27,"division_rank":9,"pace":"13:22","time":"22:21:41"},{"name":"Ted Schultz","sex":"M","age":32,"bib":"804","hometown":"Colorado Springs, CO, USA","rank":30,"gender_rank":28,"division_rank":10,"pace":"13:23","time":"22:24:12"},{"name":"Wesley Sandoval","sex":"M","age":45,"bib":"103","hometown":"Leadville, CO, USA","rank":31,"gender_rank":29,"division_rank":9,"pace":"13:28","time":"22:31:29"},{"name":"Ryan Guldan","sex":"M","age":38,"bib":"520","hometown":"Grand Junction, CO, USA","rank":32,"gender_rank":30,"division_rank":11,"pace":"13:35","time":"22:43:27"},{"name":"Francesco Perini","sex":"M","age":36,"bib":"738","hometown":"Casier, -, ITA","rank":33,"gender_rank":31,"division_rank":12,"pace":"13:36","time":"22:45:54"},{"name":"Ryan Van Duzer","sex":"M","age":43,"bib":"57","hometown":"Boulder, CO, USA","rank":34,"gender_rank":32,"division_rank":10,"pace":"13:38","time":"22:49:29"},{"name":"Leonardo Santillana","sex":"M","age":37,"bib":"799","hometown":"Las Vegas, NV, USA","rank":35,"gender_rank":33,"division_rank":13,"pace":"13:38","time":"22:49:32"},{"name":"Lindsey Herman","sex":"F","age":24,"bib":"11","hometown":"Gunnison, CO, USA","rank":36,"gender_rank":3,"division_rank":1,"pace":"13:39","time":"22:50:41"},{"name":"Brian Husmann","sex":"M","age":50,"bib":"306","hometown":"Denver, CO, USA","rank":37,"gender_rank":34,"division_rank":2,"pace":"13:42","time":"22:55:42"},{"name":"Eric Holmstead","sex":"M","age":29,"bib":"554","hometown":"Denver, CO, USA","rank":38,"gender_rank":35,"division_rank":7,"pace":"13:43","time":"22:56:32"},{"name":"Chris Wright","sex":"M","age":50,"bib":"110","hometown":"Grand Junction, CO, USA","rank":39,"gender_rank":36,"division_rank":3,"pace":"13:45","time":"23:00:48"},{"name":"Benjamin Boese","sex":"M","age":33,"bib":"380","hometown":"Gypsum, CO, USA","rank":40,"gender_rank":37,"division_rank":14,"pace":"13:48","time":"23:04:59"},{"name":"Robert Strickland","sex":"M","age":42,"bib":"196","hometown":"Englewood, CO, USA","rank":41,"gender_rank":38,"division_rank":11,"pace":"13:51","time":"23:11:00"},{"name":"Patrick McClellan","sex":"M","age":27,"bib":"662","hometown":"Austin, TX, USA","rank":42,"gender_rank":39,"division_rank":8,"pace":"13:55","time":"23:17:54"},{"name":"Ryan Charter","sex":"M","age":33,"bib":"425","hometown":"Leadville, CO, USA","rank":43,"gender_rank":40,"division_rank":15,"pace":"13:56","time":"23:19:30"},{"name":"Roxanne Vogel","sex":"F","age":37,"bib":"898","hometown":"Mammoth Lakes, CA, USA","rank":44,"gender_rank":4,"division_rank":2,"pace":"13:58","time":"23:21:33"},{"name":"Tim Hoppin","sex":"M","age":41,"bib":"186","hometown":"Steamboat Springs, CO, USA","rank":45,"gender_rank":41,"division_rank":12,"pace":"13:59","time":"23:23:53"},{"name":"Jason Clarke","sex":"M","age":35,"bib":"428","hometown":"Montrose, CO, USA","rank":46,"gender_rank":42,"division_rank":16,"pace":"14:00","time":"23:25:18"},{"name":"Eric Pepper","sex":"M","age":43,"bib":"735","hometown":"Wolcott, CO, USA","rank":47,"gender_rank":43,"division_rank":13,"pace":"14:01","time":"23:27:46"},{"name":"COREY KALLEMBACH","sex":"M","age":33,"bib":"187","hometown":"Longmont, CO, USA","rank":48,"gender_rank":44,"division_rank":17,"pace":"14:01","time":"23:28:03"},{"name":"Max Kilcoyne","sex":"M","age":18,"bib":"40","hometown":"Louisville, CO, USA","rank":49,"gender_rank":45,"division_rank":1,"pace":"14:05","time":"23:33:27"},{"name":"Matthew Berdine","sex":"M","age":43,"bib":"373","hometown":"Centennial, CO, USA","rank":50,"gender_rank":46,"division_rank":14,"pace":"14:12","time":"23:45:04"}]
[{"name":"Adam Wolf","sex":"M","age":44,"bib":"929","hometown":"Petaluma, CA, USA","rank":51,"gender_rank":47,"division_rank":15,"pace":"14:16","time":"23:52:37"},{"name":"Noah Schaich","sex":"M","age":26,"bib":"803","hometown":"Fort Collins, CO, USA","rank":52,"gender_rank":48,"division_rank":9,"pace":"14:18","time":"23:55:43"},{"name":"Madeline Hirschfeld","sex":"F","age":29,"bib":"549","hometown":"Telluride, CO, USA","rank":53,"gender_rank":5,"division_rank":2,"pace":"14:19","time":"23:57:45"},{"name":"Bruce Dailey","sex":"M","age":51,"bib":"32","hometown":"Leadville, CO, USA","rank":54,"gender_rank":49,"division_rank":4,"pace":"14:20","time":"23:59:52"},{"name":"Michael Nanaszko","sex":"M","age":40,"bib":"942","hometown":"Salem, OR, USA","rank":55,"gender_rank":50,"division_rank":16,"pace":"14:21","time":"24:00:21"},{"name":"Paul Steinweg","sex":"M","age":41,"bib":"849","hometown":"Breckenridge, CO, USA","rank":56,"gender_rank":51,"division_rank":17,"pace":"14:21","time":"24:01:02"},{"name":"Brian Turner","sex":"M","age":35,"bib":"883","hometown":"Adrian, MI, USA","rank":57,"gender_rank":52,"division_rank":18,"pace":"14:21","time":"24:01:16"},{"name":"Peter Hogg","sex":"M","age":39,"bib":"553","hometown":"Indianapolis, IN, USA","rank":58,"gender_rank":53,"division_rank":19,"pace":"14:25","time":"24:07:10"},{"name":"Brian Klug","sex":"M","age":43,"bib":"590","hometown":"Saint Cloud, MN, USA","rank":59,"gender_rank":54,"division_rank":18,"pace":"14:30","time":"24:16:06"},{"name":"Rachel Brewer","sex":"F","age":42,"bib":"393","hometown":"Golden, CO, USA","rank":60,"gender_rank":6,"division_rank":1,"pace":"14:31","time":"24:17:29"},{"name":"Kris Rugloski","sex":"F","age":25,"bib":"788","hometown":"West Columbia, TX, USA","rank":61,"gender_rank":7,"division_rank":3,"pace":"14:31","time":"24:18:14"},{"name":"Samantha Wood","sex":"F","age":37,"bib":"112","hometown":"Manitou Springs, CO, USA","rank":62,"gender_rank":8,"division_rank":3,"pace":"14:33","time":"24:20:11"},{"name":"Max Riehemann","sex":"M","age":29,"bib":"770","hometown":"Denver, CO, USA","rank":63,"gender_rank":55,"division_rank":10,"pace":"14:34","time":"24:22:19"},{"name":"Neil Feldman","sex":"M","age":52,"bib":"137","hometown":"Boylston, MA, USA","rank":64,"gender_rank":56,"division_rank":5,"pace":"14:34","time":"24:23:04"},{"name":"Kevin Carson","sex":"M","age":31,"bib":"420","hometown":"Dillon, CO, USA","rank":65,"gender_rank":57,"division_rank":20,"pace":"14:35","time":"24:24:52"},{"name":"Piers Constable","sex":"M","age":51,"bib":"216","hometown":"New York, NY, USA","rank":66,"gender_rank":58,"division_rank":6,"pace":"14:38","time":"24:29:24"},{"name":"Drew Petersen","sex":"M","age":28,"bib":"741","hometown":"Silverthorne, CO, USA","rank":67,"gender_rank":59,"division_rank":11,"pace":"14:40","time":"24:32:03"},{"name":"Larry Smith","sex":"M","age":52,"bib":"56","hometown":"Leadville, CO, USA","rank":68,"gender_rank":60,"division_rank":7,"pace":"14:40","time":"24:32:15"},{"name":"Kirill Minkovich","sex":"M","age":40,"bib":"682","hometown":"Redwood City, CA, USA","rank":69,"gender_rank":61,"division_rank":19,"pace":"14:40","time":"24:32:40"},{"name":"Jonathan Clinthorne","sex":"M","age":35,"bib":"180","hometown":"Denver, CO, USA","rank":70,"gender_rank":62,"division_rank":21,"pace":"14:41","time":"24:33:58"},{"name":"Peter Polito","sex":"M","age":38,"bib":"750","hometown":"Austin, TX, USA","rank":71,"gender_rank":63,"division_rank":22,"pace":"14:41","time":"24:34:02"},{"name":"David Miao","sex":"M","age":57,"bib":"679","hometown":"Flushing, NY, USA","rank":72,"gender_rank":64,"division_rank":8,"pace":"14:41","time":"24:34:02"},{"name":"Jacob Sheetz-Willard","sex":"M","age":32,"bib":"46","hometown":"Leadville, CO, USA","rank":73,"gender_rank":65,"division_rank":23,"pace":"14:42","time":"24:36:27"},{"name":"Shelby Johnson","sex":"F","age":36,"bib":"571","hometown":"Colorado Springs, CO, USA","rank":74,"gender_rank":9,"division_rank":4,"pace":"14:43","time":"24:37:32"},{"name":"BRIAN TOY","sex":"M","age":44,"bib":"880","hometown":"Pike Road, AL, USA","rank":75,"gender_rank":66,"division_rank":20,"pace":"14:46","time":"24:41:47"},{"name":"Michael New","sex":"M","age":45,"bib":"288","hometown":"Evansville, MN, USA","rank":76,"gender_rank":67,"division_rank":21,"pace":"14:46","time":"24:42:09"},{"name":"Don Reichelt","sex":"M","age":36,"bib":"766","hometown":"Fairplay, CO, USA","rank":77,"gender_rank":68,"division_rank":24,"pace":"14:46","time":"24:42:12"},{"name":"David Duede","sex":"M","age":43,"bib":"278","hometown":"Eagan, MN, USA","rank":78,"gender_rank":69,"division_rank":22,"pace":"14:46","time":"24:42:16"},{"name":"Bedrich Stancik","sex":"M","age":38,"bib":"847","hometown":"Havířov, -, CZE","rank":79,"gender_rank":70,"division_rank":25,"pace":"14:47","time":"24:43:30"},{"name":"Rob Kelsey","sex":"M","age":47,"bib":"585","hometown":"Danville, IL, USA","rank":80,"gender_rank":71,"division_rank":23,"pace":"14:48","time":"24:46:23"},{"name":"John Pedrosa","sex":"M","age":40,"bib":"729","hometown":"Fort Collins, CO, USA","rank":81,"gender_rank":72,"division_rank":24,"pace":"14:50","time":"24:48:33"},{"name":"Chris Kelly","sex":"M","age":40,"bib":"264","hometown":"Aspen, CO, USA","rank":82,"gender_rank":73,"division_rank":25,"pace":"14:52","time":"24:52:15"},{"name":"Darian Allberry","sex":"M","age":26,"bib":"343","hometown":"Denver, CO, USA","rank":83,"gender_rank":74,"division_rank":12,"pace":"14:52","time":"24:53:12"},{"name":"Kevin Linebarger","sex":"M","age":41,"bib":"621","hometown":"Leadville, CO, USA","rank":84,"gender_rank":75,"division_rank":26,"pace":"14:53","time":"24:53:27"},{"name":"Aaron Anton","sex":"M","age":40,"bib":"349","hometown":"Eldorado Springs, CO, USA","rank":85,"gender_rank":76,"division_rank":27,"pace":"14:55","time":"24:58:10"},{"name":"MAX FULTON","sex":"M","age":45,"bib":"107","hometown":"Wheat Ridge, CO, USA","rank":86,"gender_rank":77,"division_rank":28,"pace":"15:02","time":"25:08:37"},{"name":"April McAnly","sex":"F","age":40,"bib":"654","hometown":"Eagle River, AK, USA","rank":87,"gender_rank":10,"division_rank":2,"pace":"15:03","time":"25:11:03"},{"name":"Nathan Sicher","sex":"M","age":41,"bib":"814","hometown":"Webb City, MO, USA","rank":88,"gender_rank":78,"division_rank":29,"pace":"15:08","time":"25:19:14"},{"name":"Robert Ankarlo","sex":"M","age":29,"bib":"348","hometown":"Denver, CO, USA","rank":89,"gender_rank":79,"division_rank":13,"pace":"15:09","time":"25:21:22"},{"name":"Pierce Showe","sex":"M","age":21,"bib":"813","hometown":"The Colony, TX, USA","rank":90,"gender_rank":80,"division_rank":14,"pace":"15:11","time":"25:24:32"},{"name":"Martin Almazan","sex":"M","age":32,"bib":"345","hometown":"Vail, CO, USA","rank":91,"gender_rank":81,"division_rank":26,"pace":"15:11","time":"25:25:04"},{"name":"Mathieu Shields","sex":"M","age":36,"bib":"812","hometown":"Boulder, CO, USA","rank":92,"gender_rank":82,"division_rank":27,"pace":"15:14","time":"25:28:52"},{"name":"Abe Kane","sex":"M","age":33,"bib":"579","hometown":"Kalamazoo, MI, USA","rank":93,"gender_rank":83,"division_rank":28,"pace":"15:19","time":"25:37:41"},{"name":"Kendall Dinwiddie","sex":"F","age":36,"bib":"461","hometown":"Austin, TX, USA","rank":94,"gender_rank":11,"division_rank":5,"pace":"15:20","time":"25:39:14"},{"name":"Jolene Sandoval","sex":"F","age":47,"bib":"105","hometown":"Leadville, CO, USA","rank":95,"gender_rank":12,"division_rank":3,"pace":"15:22","time":"25:43:34"},{"name":"Jared Sweet","sex":"M","age":50,"bib":"89","hometown":"Las Vegas, NV, USA","rank":96,"gender_rank":84,"division_rank":9,"pace":"15:23","time":"25:45:14"},{"name":"Dustin Kessinger","sex":"M","age":38,"bib":"586","hometown":"Parker, CO, USA","rank":97,"gender_rank":85,"division_rank":29,"pace":"15:24","time":"25:46:31"},{"name":"Andrew Elvester","sex":"M","age":43,"bib":"279","hometown":"Minneapolis, MN, USA","rank":98,"gender_rank":86,"division_rank":30,"pace":"15:25","time":"25:47:16"},{"name":"Kay Borleis","sex":"F","age":36,"bib":"383","hometown":"Boulder, CO, USA","rank":99,"gender_rank":13,"division_rank":6,"pace":"15:27","time":"25:51:29"},{"name":"Elizabeth Helland","sex":"F","age":44,"bib":"537","hometown":"Colorado Springs, CO, USA","rank":100,"gender_rank":14,"division_rank":4,"pace":"15:31","time":"25:57:57"}]
[{"name":"Megan Eckert","sex":"F","age":36,"bib":"471","hometown":"Santa Fe, NM, USA","rank":101,"gender_rank":15,"division_rank":7,"pace":"15:31","time":"25:58:22"},{"name":"Kayde Anderson","sex":"F","age":39,"bib":"140","hometown":"Thornton, CO, USA","rank":102,"gender_rank":16,"division_rank":8,"pace":"15:31","time":"25:58:31"},{"name":"Kate LeVasseur","sex":"F","age":37,"bib":"614","hometown":"Wheatridge, CO, USA","rank":103,"gender_rank":17,"division_rank":9,"pace":"15:33","time":"26:01:49"},{"name":"Jordan Akiyoshi","sex":"M","age":27,"bib":"245","hometown":"Napa, CA, USA","rank":104,"gender_rank":87,"division_rank":15,"pace":"15:36","time":"26:06:14"},{"name":"Trevor Heller","sex":"M","age":30,"bib":"538","hometown":"Brighton, MA, USA","rank":105,"gender_rank":88,"division_rank":30,"pace":"15:36","time":"26:06:18"},{"name":"Ash Walsh","sex":"F","age":35,"bib":"901","hometown":"Bethlehem, GA, USA","rank":106,"gender_rank":18,"division_rank":10,"pace":"15:41","time":"26:14:13"},{"name":"Katy Anderson","sex":"F","age":45,"bib":"23","hometown":"Bondi Beach, -, AUS","rank":107,"gender_rank":19,"division_rank":5,"pace":"15:43","time":"26:17:48"},{"name":"Andrew Stanley","sex":"M","age":59,"bib":"330","hometown":"Rotorua, -, NZL","rank":108,"gender_rank":89,"division_rank":10,"pace":"15:45","time":"26:20:33"},{"name":"Alexander Kellam","sex":"M","age":23,"bib":"584","hometown":"Fort Collins, CO, USA","rank":109,"gender_rank":90,"division_rank":16,"pace":"15:45","time":"26:21:33"},{"name":"Brooks Williams","sex":"M","age":39,"bib":"921","hometown":"Colorado Springs, CO, USA","rank":110,"gender_rank":91,"division_rank":31,"pace":"15:46","time":"26:22:50"},{"name":"Emily Luhrs","sex":"F","age":32,"bib":"631","hometown":"Chicago, IL, USA","rank":111,"gender_rank":20,"division_rank":11,"pace":"15:46","time":"26:22:50"},{"name":"Perry Curiston","sex":"M","age":53,"bib":"444","hometown":"Markham, ONTARIO, CAN","rank":112,"gender_rank":92,"division_rank":11,"pace":"15:50","time":"26:28:57"},{"name":"Michael Oliva","sex":"M","age":43,"bib":"719","hometown":"Superior, CO, USA","rank":113,"gender_rank":93,"division_rank":31,"pace":"15:51","time":"26:30:55"},{"name":"Gergely Medgyessy","sex":"M","age":51,"bib":"673","hometown":"Budapest, -, HUN","rank":114,"gender_rank":94,"division_rank":12,"pace":"15:54","time":"26:36:18"},{"name":"Kevin Bliss","sex":"M","age":45,"bib":"378","hometown":"Woodstock, NY, USA","rank":115,"gender_rank":95,"division_rank":32,"pace":"15:57","time":"26:41:40"},{"name":"Erik Brandner","sex":"M","age":36,"bib":"391","hometown":"Eagan, MN, USA","rank":116,"gender_rank":96,"division_rank":32,"pace":"16:00","time":"26:46:58"},{"name":"Gwen Golaszewski","sex":"F","age":34,"bib":"13","hometown":"Louisville, CO, USA","rank":117,"gender_rank":21,"division_rank":12,"pace":"16:05","time":"26:55:05"},{"name":"SHINSUKE ISOMURA","sex":"M","age":43,"bib":"275","hometown":"Hayama, KANAGAWA / 神奈川県, JPN","rank":118,"gender_rank":97,"division_rank":33,"pace":"16:07","time":"26:58:14"},{"name":"Paul Prawdzik","sex":"M","age":26,"bib":"753","hometown":"Salt Lake City, UT, USA","rank":119,"gender_rank":98,"division_rank":17,"pace":"16:09","time":"27:01:46"},{"name":"Henry Fischer","sex":"M","age":55,"bib":"483","hometown":"Denver, CO, USA","rank":120,"gender_rank":99,"division_rank":13,"pace":"16:10","time":"27:02:57"},{"name":"Alex Falconer","sex":"M","age":41,"bib":"479","hometown":"Eden Prairie, MN, USA","rank":121,"gender_rank":100,"division_rank":34,"pace":"16:10","time":"27:03:37"},{"name":"Nate Glocke","sex":"M","age":31,"bib":"508","hometown":"Boulder, CO, USA","rank":122,"gender_rank":101,"division_rank":33,"pace":"16:12","time":"27:05:44"},{"name":"Tim Cronk","sex":"M","age":60,"bib":"145","hometown":"Tucson, AZ, USA","rank":123,"gender_rank":102,"division_rank":1,"pace":"16:14","time":"27:09:47"},{"name":"Dani Reese","sex":"F","age":33,"bib":"764","hometown":"Bend, OR, USA","rank":124,"gender_rank":22,"division_rank":13,"pace":"16:15","time":"27:11:35"},{"name":"Noah Sosin","sex":"M","age":32,"bib":"835","hometown":"Leadville, CO, USA","rank":125,"gender_rank":103,"division_rank":34,"pace":"16:16","time":"27:14:00"},{"name":"Ivan O' Gorman","sex":"M","age":44,"bib":"171","hometown":"Limerick, -, IRL","rank":126,"gender_rank":104,"division_rank":35,"pace":"16:17","time":"27:14:48"},{"name":"Sanami Fottral","sex":"F","age":42,"bib":"489","hometown":"San Antonio, TX, USA","rank":127,"gender_rank":23,"division_rank":6,"pace":"16:18","time":"27:16:12"},{"name":"Kris Winslett","sex":"M","age":41,"bib":"925","hometown":"Austin, TX, USA","rank":128,"gender_rank":105,"division_rank":36,"pace":"16:18","time":"27:16:46"},{"name":"Patrick Atkinson","sex":"M","age":37,"bib":"353","hometown":"Wilmington, DE, USA","rank":129,"gender_rank":106,"division_rank":35,"pace":"16:18","time":"27:17:20"},{"name":"Todd Stiefler","sex":"M","age":44,"bib":"852","hometown":"Bethesda, MD, USA","rank":130,"gender_rank":107,"division_rank":37,"pace":"16:19","time":"27:17:25"},{"name":"Nick Harreld","sex":"M","age":35,"bib":"532","hometown":"Albuquerque, NM, USA","rank":131,"gender_rank":108,"division_rank":36,"pace":"16:19","time":"27:18:20"},{"name":"Eugene Betty","sex":"M","age":50,"bib":"308","hometown":"Broomfield, CO, USA","rank":132,"gender_rank":109,"division_rank":14,"pace":"16:20","time":"27:20:27"},{"name":"Thomas McPhaul","sex":"M","age":26,"bib":"244","hometown":"Baltimore, MD, USA","rank":133,"gender_rank":110,"division_rank":18,"pace":"16:21","time":"27:21:00"},{"name":"Lisa Albers","sex":"F","age":49,"bib":"340","hometown":"Highlands Ranch, CO, USA","rank":134,"gender_rank":24,"division_rank":7,"pace":"16:23","time":"27:25:23"},{"name":"John Diana","sex":"M","age":53,"bib":"220","hometown":"Napa, CA, USA","rank":135,"gender_rank":111,"division_rank":15,"pace":"16:27","time":"27:32:04"},{"name":"Sierra DeGroff","sex":"F","age":31,"bib":"455","hometown":"Las Vegas, NV, USA","rank":136,"gender_rank":25,"division_rank":14,"pace":"16:28","time":"27:32:47"},{"name":"Jonathan Norloff","sex":"M","age":35,"bib":"192","hometown":"Westminster, CO, USA","rank":137,"gender_rank":112,"division_rank":37,"pace":"16:29","time":"27:34:51"},{"name":"Michael Sager","sex":"M","age":37,"bib":"796","hometown":"Denver, CO, USA","rank":138,"gender_rank":113,"division_rank":38,"pace":"16:29","time":"27:35:01"},{"name":"Scott Marten","sex":"M","age":54,"bib":"647","hometown":"Berthoud, CO, USA","rank":139,"gender_rank":114,"division_rank":16,"pace":"16:29","time":"27:35:40"},{"name":"William Rushforth","sex":"M","age":37,"bib":"789","hometown":"Los Angeles, CA, USA","rank":140,"gender_rank":115,"division_rank":39,"pace":"16:30","time":"27:36:08"},{"name":"Brad Slighting","sex":"M","age":45,"bib":"824","hometown":"Las Vegas, NV, USA","rank":141,"gender_rank":116,"division_rank":38,"pace":"16:31","time":"27:38:47"},{"name":"Megan Flanagan","sex":"F","age":27,"bib":"41","hometown":"Golden, CO, USA","rank":142,"gender_rank":26,"division_rank":4,"pace":"16:31","time":"27:38:48"},{"name":"Gary Geer","sex":"M","age":55,"bib":"222","hometown":"Willmar, MN, USA","rank":143,"gender_rank":117,"division_rank":17,"pace":"16:32","time":"27:40:24"},{"name":"Michael Curry","sex":"M","age":35,"bib":"445","hometown":"Los Angeles, CA, USA","rank":144,"gender_rank":118,"division_rank":40,"pace":"16:33","time":"27:42:02"},{"name":"Jenna Carosio","sex":"F","age":32,"bib":"419","hometown":"Arvada, CO, USA","rank":145,"gender_rank":27,"division_rank":15,"pace":"16:34","time":"27:43:12"},{"name":"Hellah Sidibe","sex":"M","age":31,"bib":"24","hometown":"Rochelle Park, NJ, USA","rank":146,"gender_rank":119,"division_rank":41,"pace":"16:35","time":"27:44:09"},{"name":"Tatiana Rypinski","sex":"F","age":29,"bib":"792","hometown":"Houston, TX, USA","rank":147,"gender_rank":28,"division_rank":5,"pace":"16:35","time":"27:44:56"},{"name":"Samantha Hurlbutt","sex":"F","age":41,"bib":"562","hometown":"Jersey Shore, PA, USA","rank":148,"gender_rank":29,"division_rank":8,"pace":"16:36","time":"27:45:54"},{"name":"Maik Becker","sex":"M","age":52,"bib":"368","hometown":"Zurich, -, CHE","rank":149,"gender_rank":120,"division_rank":18,"pace":"16:36","time":"27:46:00"},{"name":"Josh Gall","sex":"M","age":31,"bib":"497","hometown":"Longmont, CO, USA","rank":150,"gender_rank":121,"division_rank":42,"pace":"16:36","time":"27:47:09"}]
[{"name":"Peter Mack","sex":"M","age":42,"bib":"636","hometown":"Lafayette, CO, USA","rank":151,"gender_rank":122,"division_rank":39,"pace":"16:37","time":"27:47:41"},{"name":"Paul Schoenlaub","sex":"M","age":63,"bib":"28","hometown":"St. Joseph, MO, USA","rank":152,"gender_rank":123,"division_rank":2,"pace":"16:37","time":"27:47:44"},{"name":"Kara Diamond-Husmann","sex":"F","age":45,"bib":"285","hometown":"Denver, CO, USA","rank":153,"gender_rank":30,"division_rank":9,"pace":"16:37","time":"27:48:05"},{"name":"John Stanley","sex":"M","age":55,"bib":"195","hometown":"Denver, CO, USA","rank":154,"gender_rank":124,"division_rank":19,"pace":"16:38","time":"27:49:38"},{"name":"DANIEL PRITCHARD","sex":"M","age":43,"bib":"283","hometown":"Steamboat Springs, CO, USA","rank":155,"gender_rank":125,"division_rank":40,"pace":"16:38","time":"27:50:13"},{"name":"TIMOTHY BARR","sex":"M","age":46,"bib":"136","hometown":"Arvada, CO, USA","rank":156,"gender_rank":126,"division_rank":41,"pace":"16:38","time":"27:50:42"},{"name":"Miguel Perez","sex":"M","age":39,"bib":"737","hometown":"Colorado Springs, CO, USA","rank":157,"gender_rank":127,"division_rank":43,"pace":"16:39","time":"27:51:04"},{"name":"Simon Guerard","sex":"M","age":36,"bib":"200","hometown":"Carlsbad, CA, USA","rank":158,"gender_rank":128,"division_rank":44,"pace":"16:39","time":"27:51:25"},{"name":"Christopher Minton","sex":"M","age":46,"bib":"203","hometown":"Seattle, WA, USA","rank":159,"gender_rank":129,"division_rank":42,"pace":"16:40","time":"27:53:05"},{"name":"Nick Smarrelli","sex":"M","age":40,"bib":"826","hometown":"Westfield, IN, USA","rank":160,"gender_rank":130,"division_rank":43,"pace":"16:40","time":"27:53:32"},{"name":"Collin Morris","sex":"M","age":35,"bib":"934","hometown":"Spring Hill, TN, USA","rank":161,"gender_rank":131,"division_rank":45,"pace":"16:40","time":"27:53:40"},{"name":"Christopher Nicholas","sex":"M","age":45,"bib":"289","hometown":"Rogers, AR, USA","rank":162,"gender_rank":132,"division_rank":44,"pace":"16:40","time":"27:54:02"},{"name":"Dolan Potts","sex":"M","age":38,"bib":"143","hometown":"Salida, CO, USA","rank":163,"gender_rank":133,"division_rank":46,"pace":"16:41","time":"27:54:45"},{"name":"Jeremy Segal","sex":"M","age":37,"bib":"809","hometown":"Saint Paul, MN, USA","rank":164,"gender_rank":134,"division_rank":47,"pace":"16:41","time":"27:54:47"},{"name":"Tess Hamilton","sex":"F","age":27,"bib":"529","hometown":"Boulder, CO, USA","rank":165,"gender_rank":31,"division_rank":6,"pace":"16:41","time":"27:54:53"},{"name":"Bram Blondelle","sex":"M","age":40,"bib":"379","hometown":"Heffen, -, BEL","rank":166,"gender_rank":135,"division_rank":45,"pace":"16:41","time":"27:55:11"},{"name":"Brent Harder","sex":"M","age":30,"bib":"531","hometown":"Evergreen, CO, USA","rank":167,"gender_rank":136,"division_rank":48,"pace":"16:42","time":"27:56:49"},{"name":"Tommy Padia","sex":"M","age":27,"bib":"724","hometown":"Aspen, CO, USA","rank":168,"gender_rank":137,"division_rank":19,"pace":"16:43","time":"27:58:23"},{"name":"Nicholas Mullen","sex":"M","age":37,"bib":"698","hometown":"Windsor, CO, USA","rank":169,"gender_rank":138,"division_rank":49,"pace":"16:44","time":"27:59:19"},{"name":"Heather Kopsky","sex":"F","age":31,"bib":"598","hometown":"Buena Vista, CO, USA","rank":170,"gender_rank":32,"division_rank":16,"pace":"16:44","time":"27:59:54"},{"name":"Karl Huchthausen","sex":"M","age":42,"bib":"557","hometown":"Frisco, TX, USA","rank":171,"gender_rank":139,"division_rank":46,"pace":"16:45","time":"28:01:03"},{"name":"Matthew Burdette","sex":"M","age":40,"bib":"406","hometown":"Churchville, MD, USA","rank":172,"gender_rank":140,"division_rank":47,"pace":"16:45","time":"28:01:12"},{"name":"Todd Meconis","sex":"M","age":47,"bib":"672","hometown":"Smyrna, GA, USA","rank":173,"gender_rank":141,"division_rank":48,"pace":"16:47","time":"28:04:39"},{"name":"Breanna Cornell","sex":"F","age":30,"bib":"438","hometown":"Flagstaff, AZ, USA","rank":174,"gender_rank":33,"division_rank":17,"pace":"16:47","time":"28:05:19"},{"name":"Abraham Bejil","sex":"M","age":42,"bib":"369","hometown":"Midland, TX, USA","rank":175,"gender_rank":142,"division_rank":49,"pace":"16:47","time":"28:05:46"},{"name":"David Long","sex":"M","age":58,"bib":"626","hometown":"Kalispell, MT, USA","rank":176,"gender_rank":143,"division_rank":20,"pace":"16:49","time":"28:08:24"},{"name":"Diego Garcia","sex":"M","age":42,"bib":"499","hometown":"Santiago, -, CHL","rank":177,"gender_rank":144,"division_rank":50,"pace":"16:50","time":"28:09:48"},{"name":"Andrew Catalano","sex":"M","age":35,"bib":"212","hometown":"Bloomington, IL, USA","rank":178,"gender_rank":145,"division_rank":50,"pace":"16:51","time":"28:12:15"},{"name":"Marcelo Arias Massa","sex":"M","age":39,"bib":"350","hometown":"Santiago, -, CHL","rank":179,"gender_rank":146,"division_rank":51,"pace":"16:52","time":"28:12:55"},{"name":"Todd Pizzi","sex":"M","age":48,"bib":"148","hometown":"San Diego, CA, USA","rank":180,"gender_rank":147,"division_rank":51,"pace":"16:52","time":"28:14:01"},{"name":"Jan Olsson","sex":"M","age":65,"bib":"720","hometown":"Gaevle, -, SWE","rank":181,"gender_rank":148,"division_rank":3,"pace":"16:52","time":"28:14:08"},{"name":"Chris Lantzy","sex":"M","age":43,"bib":"606","hometown":"Sedona, AZ, USA","rank":182,"gender_rank":149,"division_rank":52,"pace":"16:54","time":"28:16:17"},{"name":"Phil Atkinson","sex":"M","age":50,"bib":"354","hometown":"Billings, MT, USA","rank":183,"gender_rank":150,"division_rank":21,"pace":"16:54","time":"28:16:28"},{"name":"Travis Tung","sex":"M","age":41,"bib":"269","hometown":"Las Vegas, NV, USA","rank":184,"gender_rank":151,"division_rank":53,"pace":"16:54","time":"28:16:39"},{"name":"John Molloy","sex":"M","age":39,"bib":"265","hometown":"Christchurch, -, NZL","rank":185,"gender_rank":152,"division_rank":52,"pace":"16:54","time":"28:16:52"},{"name":"John Minkema","sex":"M","age":46,"bib":"293","hometown":"Modesto, CA, USA","rank":186,"gender_rank":153,"division_rank":54,"pace":"16:55","time":"28:17:47"},{"name":"Junko Kazukawa","sex":"F","age":59,"bib":"59","hometown":"Denver, CO, USA","rank":187,"gender_rank":34,"division_rank":1,"pace":"16:55","time":"28:17:51"},{"name":"Gary Lampman","sex":"M","age":57,"bib":"604","hometown":"Ridgway, PA, USA","rank":188,"gender_rank":154,"division_rank":22,"pace":"16:55","time":"28:18:59"},{"name":"Matthew Tarver","sex":"M","age":38,"bib":"868","hometown":"Allen, TX, USA","rank":189,"gender_rank":155,"division_rank":53,"pace":"16:57","time":"28:22:20"},{"name":"Kristin Gablehouse","sex":"F","age":44,"bib":"286","hometown":"Broomfield, CO, USA","rank":190,"gender_rank":35,"division_rank":10,"pace":"16:57","time":"28:22:22"},{"name":"Jason Friedman","sex":"M","age":41,"bib":"491","hometown":"Morristown, NJ, USA","rank":191,"gender_rank":156,"division_rank":55,"pace":"16:59","time":"28:24:30"},{"name":"Jonathan Prosser","sex":"M","age":32,"bib":"754","hometown":"Topeka, KS, USA","rank":192,"gender_rank":157,"division_rank":54,"pace":"16:59","time":"28:24:47"},{"name":"Beau Brooks","sex":"M","age":41,"bib":"395","hometown":"Castle Rock, CO, USA","rank":193,"gender_rank":158,"division_rank":56,"pace":"16:59","time":"28:25:27"},{"name":"Sam Schwaller","sex":"M","age":35,"bib":"805","hometown":"Collierville, TN, USA","rank":194,"gender_rank":159,"division_rank":55,"pace":"17:00","time":"28:26:34"},{"name":"Mason McWilliams","sex":"M","age":44,"bib":"282","hometown":"Memphis, TN, USA","rank":195,"gender_rank":160,"division_rank":57,"pace":"17:01","time":"28:27:57"},{"name":"Sarah Hodges","sex":"F","age":36,"bib":"550","hometown":"Heber City, UT, USA","rank":196,"gender_rank":36,"division_rank":18,"pace":"17:02","time":"28:29:49"},{"name":"Brad Stahlman","sex":"M","age":42,"bib":"846","hometown":"Choctaw, OK, USA","rank":197,"gender_rank":161,"division_rank":58,"pace":"17:02","time":"28:29:57"},{"name":"Sergio Saenz","sex":"M","age":53,"bib":"795","hometown":"Denver, CO, USA","rank":198,"gender_rank":162,"division_rank":23,"pace":"17:02","time":"28:30:08"},{"name":"Joel Beskar","sex":"M","age":41,"bib":"168","hometown":"New Richmond, WI, USA","rank":199,"gender_rank":163,"division_rank":59,"pace":"17:03","time":"28:32:04"},{"name":"Peter Keirn","sex":"M","age":38,"bib":"583","hometown":"Lacey, WA, USA","rank":200,"gender_rank":164,"division_rank":56,"pace":"17:03","time":"28:32:28"}]
[{"name":"Jerry Scrogham","sex":"M","age":49,"bib":"808","hometown":"Shelbyville, KY, USA","rank":201,"gender_rank":165,"division_rank":60,"pace":"17:03","time":"28:32:30"},{"name":"Greg Newman","sex":"M","age":47,"bib":"707","hometown":"Golden, CO, USA","rank":202,"gender_rank":166,"division_rank":61,"pace":"17:04","time":"28:32:49"},{"name":"Neil Smith","sex":"M","age":51,"bib":"314","hometown":"Dallas, TX, USA","rank":203,"gender_rank":167,"division_rank":24,"pace":"17:04","time":"28:33:30"},{"name":"Andrew Mueller","sex":"M","age":32,"bib":"694","hometown":"Colorado Springs, CO, USA","rank":204,"gender_rank":168,"division_rank":57,"pace":"17:04","time":"28:33:42"},{"name":"Celesta Cairns","sex":"F","age":44,"bib":"415","hometown":"Leadville, CO, USA","rank":205,"gender_rank":37,"division_rank":11,"pace":"17:04","time":"28:33:59"},{"name":"Peter Hall","sex":"M","age":43,"bib":"525","hometown":"Boulder, CO, USA","rank":206,"gender_rank":169,"division_rank":62,"pace":"17:06","time":"28:37:05"},{"name":"Reid Longabaugh","sex":"M","age":25,"bib":"628","hometown":"Early, TX, USA","rank":207,"gender_rank":170,"division_rank":20,"pace":"17:07","time":"28:38:15"},{"name":"Carrie Stafford","sex":"F","age":43,"bib":"129","hometown":"Vail, CO, USA","rank":208,"gender_rank":38,"division_rank":12,"pace":"17:10","time":"28:43:46"},{"name":"Christian Robbins","sex":"M","age":51,"bib":"76","hometown":"Durango, CO, USA","rank":209,"gender_rank":171,"division_rank":25,"pace":"17:10","time":"28:44:15"},{"name":"Adam Trubow","sex":"M","age":41,"bib":"151","hometown":"Albuquerque, NM, USA","rank":210,"gender_rank":172,"division_rank":63,"pace":"17:11","time":"28:44:53"},{"name":"KEvin McCabe","sex":"M","age":42,"bib":"655","hometown":"Cary, NC, USA","rank":211,"gender_rank":173,"division_rank":64,"pace":"17:11","time":"28:45:26"},{"name":"Robert Perednia","sex":"M","age":39,"bib":"736","hometown":"Raynham, MA, USA","rank":212,"gender_rank":174,"division_rank":58,"pace":"17:11","time":"28:45:34"},{"name":"Doug Gruenbacher","sex":"M","age":49,"bib":"518","hometown":"Quinter, KS, USA","rank":213,"gender_rank":175,"division_rank":65,"pace":"17:11","time":"28:46:02"},{"name":"Charles Salsgiver","sex":"M","age":45,"bib":"797","hometown":"Finksburg, MD, USA","rank":214,"gender_rank":176,"division_rank":66,"pace":"17:12","time":"28:46:30"},{"name":"Andrea Clemons","sex":"F","age":53,"bib":"213","hometown":"Antananarivo, -, MDG","rank":215,"gender_rank":39,"division_rank":2,"pace":"17:12","time":"28:46:58"},{"name":"Charlie Ealy","sex":"M","age":59,"bib":"469","hometown":"Louisville, CO, USA","rank":216,"gender_rank":177,"division_rank":26,"pace":"17:12","time":"28:47:36"},{"name":"Oleksii Kononenko","sex":"M","age":41,"bib":"58","hometown":"Highlands Ranch, CO, USA","rank":217,"gender_rank":178,"division_rank":67,"pace":"17:13","time":"28:48:06"},{"name":"Erin MacNabb","sex":"F","age":39,"bib":"637","hometown":"Keller, TX, USA","rank":218,"gender_rank":40,"division_rank":19,"pace":"17:13","time":"28:48:10"},{"name":"Nicholas Kierstead","sex":"M","age":28,"bib":"189","hometown":"Vail, CO, USA","rank":219,"gender_rank":179,"division_rank":21,"pace":"17:13","time":"28:48:32"},{"name":"Sean Humphrey","sex":"M","age":48,"bib":"560","hometown":"Dayton, OH, USA","rank":220,"gender_rank":180,"division_rank":68,"pace":"17:13","time":"28:48:55"},{"name":"Jeff Rowthorn","sex":"M","age":44,"bib":"784","hometown":"Mount Hope, ONTARIO, CAN","rank":221,"gender_rank":181,"division_rank":69,"pace":"17:14","time":"28:49:38"},{"name":"Jeremy Couch","sex":"M","age":44,"bib":"439","hometown":"Louisville, KY, USA","rank":222,"gender_rank":182,"division_rank":70,"pace":"17:14","time":"28:50:13"},{"name":"Mike Brown","sex":"M","age":50,"bib":"396","hometown":"Edmond, OK, USA","rank":223,"gender_rank":183,"division_rank":27,"pace":"17:14","time":"28:50:41"},{"name":"Tyler Hall","sex":"M","age":50,"bib":"526","hometown":"Morgan, UT, USA","rank":224,"gender_rank":184,"division_rank":28,"pace":"17:14","time":"28:50:50"},{"name":"Mike Peter","sex":"M","age":44,"bib":"740","hometown":"Cass City, MI, USA","rank":225,"gender_rank":185,"division_rank":71,"pace":"17:15","time":"28:51:47"},{"name":"Sally McRae","sex":"F","age":43,"bib":"671","hometown":"Huntington Beach, CA, USA","rank":226,"gender_rank":41,"division_rank":13,"pace":"17:15","time":"28:52:14"},{"name":"Jeff Hirvela","sex":"M","age":43,"bib":"891","hometown":"Austin, TX, USA","rank":227,"gender_rank":186,"division_rank":72,"pace":"17:15","time":"28:52:32"},{"name":"Megan Frisk","sex":"F","age":31,"bib":"493","hometown":"Westminster, CO, USA","rank":228,"gender_rank":42,"division_rank":20,"pace":"17:16","time":"28:52:52"},{"name":"Matthew Young","sex":"M","age":48,"bib":"301","hometown":"Hurricane, WV, USA","rank":229,"gender_rank":187,"division_rank":73,"pace":"17:16","time":"28:53:24"},{"name":"Harvey Lewis","sex":"M","age":46,"bib":"15","hometown":"Cincinnati, OH, USA","rank":230,"gender_rank":188,"division_rank":74,"pace":"17:16","time":"28:53:47"},{"name":"Antonio Pizano","sex":"M","age":44,"bib":"748","hometown":"Denver, CO, USA","rank":231,"gender_rank":189,"division_rank":75,"pace":"17:17","time":"28:55:28"},{"name":"Scott Davis","sex":"M","age":43,"bib":"273","hometown":"Ponte Vedra, FL, USA","rank":232,"gender_rank":190,"division_rank":76,"pace":"17:17","time":"28:55:53"},{"name":"Gideon Scoggin","sex":"M","age":45,"bib":"296","hometown":"Germantown, TN, USA","rank":233,"gender_rank":191,"division_rank":77,"pace":"17:18","time":"28:56:32"},{"name":"Daniel Polski","sex":"M","age":44,"bib":"290","hometown":"Leadville, CO, USA","rank":234,"gender_rank":192,"division_rank":78,"pace":"17:18","time":"28:56:42"},{"name":"Elisha Tilton","sex":"M","age":49,"bib":"305","hometown":"Boulder, CO, USA","rank":235,"gender_rank":193,"division_rank":79,"pace":"17:18","time":"28:56:58"},{"name":"Bryce Weeter","sex":"M","age":37,"bib":"260","hometown":"Cary, NC, USA","rank":236,"gender_rank":194,"division_rank":59,"pace":"17:18","time":"28:57:45"},{"name":"Benjamin Jones","sex":"M","age":30,"bib":"175","hometown":"Manitowoc, WI, USA","rank":237,"gender_rank":195,"division_rank":60,"pace":"17:19","time":"28:57:49"},{"name":"Brian Smith","sex":"M","age":54,"bib":"828","hometown":"Salina, KS, USA","rank":238,"gender_rank":196,"division_rank":29,"pace":"17:19","time":"28:57:52"},{"name":"Mike Van Ryswyck","sex":"M","age":41,"bib":"890","hometown":"Barcelona, -, ESP","rank":239,"gender_rank":197,"division_rank":80,"pace":"17:19","time":"28:58:20"},{"name":"John Stubbs","sex":"M","age":44,"bib":"284","hometown":"Alexandria, VA, USA","rank":240,"gender_rank":198,"division_rank":81,"pace":"17:19","time":"28:59:15"},{"name":"JESSE ALEXANDER","sex":"M","age":55,"bib":"342","hometown":"Flagstaff, AZ, USA","rank":241,"gender_rank":199,"division_rank":30,"pace":"17:20","time":"28:59:30"},{"name":"Lisa Hallett","sex":"F","age":41,"bib":"527","hometown":"Dupont, WA, USA","rank":242,"gender_rank":43,"division_rank":14,"pace":"17:20","time":"28:59:50"},{"name":"Kate Laing","sex":"F","age":33,"bib":"250","hometown":"Littleton, CO, USA","rank":243,"gender_rank":44,"division_rank":21,"pace":"17:22","time":"29:02:52"},{"name":"Heather Griffith","sex":"F","age":35,"bib":"515","hometown":"Fayetteville, NC, USA","rank":244,"gender_rank":45,"division_rank":22,"pace":"17:22","time":"29:02:59"},{"name":"Craig Bachrodt","sex":"M","age":54,"bib":"357","hometown":"Ocala, FL, USA","rank":245,"gender_rank":200,"division_rank":31,"pace":"17:22","time":"29:03:32"},{"name":"Bonnie Alexander","sex":"F","age":36,"bib":"341","hometown":"Asheville, NC, USA","rank":246,"gender_rank":46,"division_rank":23,"pace":"17:22","time":"29:03:48"},{"name":"Julian Tonsmeire","sex":"M","age":46,"bib":"878","hometown":"Golden, CO, USA","rank":247,"gender_rank":201,"division_rank":82,"pace":"17:22","time":"29:03:56"},{"name":"Jared Bruggeman","sex":"M","age":40,"bib":"401","hometown":"Aurora, CO, USA","rank":248,"gender_rank":202,"division_rank":83,"pace":"17:22","time":"29:04:12"},{"name":"Brian Passenti","sex":"M","age":48,"bib":"117","hometown":"Glenwood Springs, CO, USA","rank":249,"gender_rank":203,"division_rank":84,"pace":"17:23","time":"29:05:00"},{"name":"Bruce Commander","sex":"M","age":45,"bib":"433","hometown":"Jacksonville, FL, USA","rank":250,"gender_rank":204,"division_rank":85,"pace":"17:23","time":"29:05:06"}]
[{"name":"Samuel Kane","sex":"M","age":29,"bib":"578","hometown":"Jackson, MI, USA","rank":251,"gender_rank":205,"division_rank":22,"pace":"17:23","time":"29:05:34"},{"name":"John Wiencek","sex":"M","age":32,"bib":"249","hometown":"Chicago, IL, USA","rank":252,"gender_rank":206,"division_rank":61,"pace":"17:24","time":"29:07:10"},{"name":"Jason Williams","sex":"M","age":38,"bib":"920","hometown":"Warwick, -, BMU","rank":253,"gender_rank":207,"division_rank":62,"pace":"17:24","time":"29:07:34"},{"name":"David Lee","sex":"M","age":43,"bib":"610","hometown":"Leadville, CO, USA","rank":254,"gender_rank":208,"division_rank":86,"pace":"17:25","time":"29:08:00"},{"name":"Patrick Sodia","sex":"M","age":59,"bib":"830","hometown":"Parker, CO, USA","rank":255,"gender_rank":209,"division_rank":32,"pace":"17:26","time":"29:09:57"},{"name":"Kyle Rodemacher","sex":"M","age":47,"bib":"775","hometown":"Austin, TX, USA","rank":256,"gender_rank":210,"division_rank":87,"pace":"17:26","time":"29:10:11"},{"name":"Brent Bozarth","sex":"M","age":29,"bib":"388","hometown":"Edmond, OK, USA","rank":257,"gender_rank":211,"division_rank":23,"pace":"17:26","time":"29:10:20"},{"name":"Amy Clark","sex":"F","age":45,"bib":"427","hometown":"Fort Worth, TX, USA","rank":258,"gender_rank":47,"division_rank":15,"pace":"17:26","time":"29:10:20"},{"name":"Tim Corliss","sex":"M","age":50,"bib":"309","hometown":"Mead, CO, USA","rank":259,"gender_rank":212,"division_rank":33,"pace":"17:27","time":"29:11:41"},{"name":"Paul Nielsen","sex":"M","age":61,"bib":"711","hometown":"Wellington, CO, USA","rank":260,"gender_rank":213,"division_rank":4,"pace":"17:27","time":"29:11:48"},{"name":"Jonathan Puskas","sex":"M","age":51,"bib":"755","hometown":"Lake Oswego, OR, USA","rank":261,"gender_rank":214,"division_rank":34,"pace":"17:27","time":"29:12:06"},{"name":"Zach Jones","sex":"M","age":35,"bib":"258","hometown":"Colorado Springs, CO, USA","rank":262,"gender_rank":215,"division_rank":63,"pace":"17:28","time":"29:13:05"},{"name":"Andrew Magalong","sex":"M","age":35,"bib":"640","hometown":"Colorado Springs, CO, USA","rank":263,"gender_rank":216,"division_rank":64,"pace":"17:28","time":"29:13:54"},{"name":"William Stoval","sex":"M","age":49,"bib":"857","hometown":"Acton, MA, USA","rank":264,"gender_rank":217,"division_rank":88,"pace":"17:29","time":"29:15:37"},{"name":"John Peyrebrune","sex":"M","age":53,"bib":"745","hometown":"Takoma Park, MD, USA","rank":265,"gender_rank":218,"division_rank":35,"pace":"17:29","time":"29:15:43"},{"name":"Michael Zettlemoyer","sex":"M","age":39,"bib":"933","hometown":"Philadelphia, PA, USA","rank":266,"gender_rank":219,"division_rank":65,"pace":"17:29","time":"29:15:48"},{"name":"Alan Villavicencio","sex":"M","age":54,"bib":"99","hometown":"Longmont, CO, USA","rank":267,"gender_rank":220,"division_rank":36,"pace":"17:30","time":"29:16:14"},{"name":"Gunnar Rogers","sex":"M","age":27,"bib":"781","hometown":"Leander, TX, USA","rank":268,"gender_rank":221,"division_rank":24,"pace":"17:30","time":"29:16:23"},{"name":"Michael Chavez","sex":"M","age":42,"bib":"138","hometown":"Arvada, CO, USA","rank":269,"gender_rank":222,"division_rank":89,"pace":"17:30","time":"29:16:48"},{"name":"Clarence Marvan","sex":"M","age":54,"bib":"326","hometown":"Denver, CO, USA","rank":270,"gender_rank":223,"division_rank":37,"pace":"17:30","time":"29:17:07"},{"name":"Mark Gaffney","sex":"M","age":46,"bib":"496","hometown":"Milton, MA, USA","rank":271,"gender_rank":224,"division_rank":90,"pace":"17:30","time":"29:17:20"},{"name":"Mandy Mullen","sex":"F","age":37,"bib":"697","hometown":"Windsor, CO, USA","rank":272,"gender_rank":48,"division_rank":24,"pace":"17:30","time":"29:17:38"},{"name":"Dan Williams","sex":"M","age":38,"bib":"919","hometown":"Franklin, TN, USA","rank":273,"gender_rank":225,"division_rank":66,"pace":"17:30","time":"29:17:42"},{"name":"Bradley MacHamer","sex":"M","age":45,"bib":"287","hometown":"Boulder, CO, USA","rank":274,"gender_rank":226,"division_rank":91,"pace":"17:31","time":"29:18:24"},{"name":"Maria Simone","sex":"F","age":48,"bib":"819","hometown":"Westminster, CO, USA","rank":275,"gender_rank":49,"division_rank":16,"pace":"17:31","time":"29:18:27"},{"name":"Matthew Pate","sex":"M","age":36,"bib":"728","hometown":"Pacific Grove, CA, USA","rank":276,"gender_rank":227,"division_rank":67,"pace":"17:31","time":"29:18:52"},{"name":"Julian Serrano","sex":"M","age":28,"bib":"811","hometown":"West Palm Beach, FL, USA","rank":277,"gender_rank":228,"division_rank":25,"pace":"17:31","time":"29:18:56"},{"name":"Jeremey Frye","sex":"M","age":34,"bib":"494","hometown":"Queensbury, NY, USA","rank":278,"gender_rank":229,"division_rank":68,"pace":"17:31","time":"29:19:18"},{"name":"Isaac Mousel","sex":"M","age":27,"bib":"692","hometown":"Denver, CO, USA","rank":279,"gender_rank":230,"division_rank":26,"pace":"17:31","time":"29:19:20"},{"name":"Scott Rubinstein","sex":"M","age":44,"bib":"786","hometown":"Littleton, CO, USA","rank":280,"gender_rank":231,"division_rank":92,"pace":"17:31","time":"29:19:20"},{"name":"John DeDoncker","sex":"M","age":58,"bib":"218","hometown":"Davenport, IA, USA","rank":281,"gender_rank":232,"division_rank":38,"pace":"17:32","time":"29:19:51"},{"name":"James Nelson","sex":"M","age":47,"bib":"702","hometown":"Prior Lake, MN, USA","rank":282,"gender_rank":233,"division_rank":93,"pace":"17:32","time":"29:20:10"},{"name":"Yuki Ikeda","sex":"M","age":42,"bib":"55","hometown":"Omeshi, TÔKYÔ / 東京都, JPN","rank":283,"gender_rank":234,"division_rank":94,"pace":"17:32","time":"29:20:14"},{"name":"Dennis Villavicencio","sex":"M","age":55,"bib":"87","hometown":"Three Rivers, CA, USA","rank":284,"gender_rank":235,"division_rank":39,"pace":"17:32","time":"29:20:40"},{"name":"Craig Stalowy","sex":"M","age":37,"bib":"238","hometown":"Littleton, CO, USA","rank":285,"gender_rank":236,"division_rank":69,"pace":"17:33","time":"29:21:39"},{"name":"CARL NORWOOD","sex":"M","age":33,"bib":"716","hometown":"Denton, TX, USA","rank":286,"gender_rank":237,"division_rank":70,"pace":"17:33","time":"29:22:20"},{"name":"Noah Pittard","sex":"M","age":49,"bib":"304","hometown":"Denver, CO, USA","rank":287,"gender_rank":238,"division_rank":95,"pace":"17:33","time":"29:22:27"},{"name":"Harry Harcrow","sex":"M","age":55,"bib":"530","hometown":"Monument, CO, USA","rank":288,"gender_rank":239,"division_rank":40,"pace":"17:33","time":"29:22:44"},{"name":"Anson Markwell","sex":"M","age":44,"bib":"281","hometown":"Frisco, TX, USA","rank":289,"gender_rank":240,"division_rank":96,"pace":"17:34","time":"29:23:05"},{"name":"Lance Parker","sex":"M","age":37,"bib":"727","hometown":"New York, NY, USA","rank":290,"gender_rank":241,"division_rank":71,"pace":"17:34","time":"29:23:15"},{"name":"John Hunt","sex":"M","age":28,"bib":"561","hometown":"Anchorage, AK, USA","rank":291,"gender_rank":242,"division_rank":27,"pace":"17:34","time":"29:24:11"},{"name":"Matthew Goldstein","sex":"M","age":49,"bib":"303","hometown":"Louisville, CO, USA","rank":292,"gender_rank":243,"division_rank":97,"pace":"17:35","time":"29:25:29"},{"name":"Lane Maher","sex":"M","age":21,"bib":"641","hometown":"Harwinton, CT, USA","rank":293,"gender_rank":244,"division_rank":28,"pace":"17:35","time":"29:25:38"},{"name":"Nicholas Marti","sex":"M","age":31,"bib":"648","hometown":"Greenville, SC, USA","rank":294,"gender_rank":245,"division_rank":72,"pace":"17:35","time":"29:25:39"},{"name":"Donald Norum","sex":"M","age":34,"bib":"715","hometown":"Charlottesville, VA, USA","rank":295,"gender_rank":246,"division_rank":73,"pace":"17:35","time":"29:25:43"},{"name":"Hollis Baugh","sex":"M","age":53,"bib":"29","hometown":"Golden, CO, USA","rank":296,"gender_rank":247,"division_rank":41,"pace":"17:35","time":"29:26:08"},{"name":"Michele Candiotto","sex":"M","age":41,"bib":"416","hometown":"Castelfranco Veneto, -, ITA","rank":297,"gender_rank":248,"division_rank":98,"pace":"17:36","time":"29:26:31"},{"name":"Jack Nermyr","sex":"M","age":25,"bib":"703","hometown":"Minneapolis, MN, USA","rank":298,"gender_rank":249,"division_rank":29,"pace":"17:36","time":"29:26:49"},{"name":"Benjamin Zeskind","sex":"U","age":39,"bib":"262","hometown":"Woodbridge, VA, USA","rank":299,"gender_rank":null,"division_rank":299,"pace":"17:36","time":"29:26:55"},{"name":"Tarah Flahavan","sex":"F","age":31,"bib":"484","hometown":"Ridgway, CO, USA","rank":300,"gender_rank":50,"division_rank":25,"pace":"17:36","time":"29:27:32"}]
[{"name":"Sarah West-Hoover","sex":"F","age":51,"bib":"909","hometown":"Parker, CO, USA","rank":301,"gender_rank":51,"division_rank":3,"pace":"17:36","time":"29:27:51"},{"name":"Maia Detmer","sex":"F","age":40,"bib":"457","hometown":"Las Vegas, NV, USA","rank":302,"gender_rank":52,"division_rank":17,"pace":"17:37","time":"29:28:02"},{"name":"Robert Cutting","sex":"M","age":51,"bib":"446","hometown":"Cassopolis, MI, USA","rank":303,"gender_rank":250,"division_rank":42,"pace":"17:37","time":"29:28:22"},{"name":"Shaun Barnes","sex":"M","age":51,"bib":"365","hometown":"Mequon, WI, USA","rank":304,"gender_rank":251,"division_rank":43,"pace":"17:37","time":"29:29:04"},{"name":"Sarah Evans","sex":"F","age":32,"bib":"474","hometown":"Buena Vista, CO, USA","rank":305,"gender_rank":53,"division_rank":26,"pace":"17:37","time":"29:29:17"},{"name":"KEITH KAZMER","sex":"M","age":44,"bib":"581","hometown":"Evergreen, CO, USA","rank":306,"gender_rank":252,"division_rank":99,"pace":"17:38","time":"29:29:37"},{"name":"Dan Morrow","sex":"M","age":31,"bib":"247","hometown":"Westfield, IN, USA","rank":307,"gender_rank":253,"division_rank":74,"pace":"17:38","time":"29:29:43"},{"name":"Chris Barnet","sex":"M","age":41,"bib":"366","hometown":"Westport, CT, USA","rank":308,"gender_rank":254,"division_rank":100,"pace":"17:38","time":"29:30:08"},{"name":"Stefan Bohdanowycz","sex":"M","age":46,"bib":"381","hometown":"Irvington, NY, USA","rank":309,"gender_rank":255,"division_rank":101,"pace":"17:38","time":"29:30:25"},{"name":"Denise Kipp","sex":"F","age":48,"bib":"588","hometown":"Eagle, CO, USA","rank":310,"gender_rank":54,"division_rank":18,"pace":"17:38","time":"29:30:27"},{"name":"Linda Haire","sex":"F","age":59,"bib":"524","hometown":"Thornton, CO, USA","rank":311,"gender_rank":55,"division_rank":4,"pace":"17:38","time":"29:30:30"},{"name":"Brandy Taylor","sex":"F","age":40,"bib":"70","hometown":"Columbia, MO, USA","rank":312,"gender_rank":56,"division_rank":19,"pace":"17:38","time":"29:30:31"},{"name":"Jed Taylor","sex":"M","age":43,"bib":"71","hometown":"Columbia, MO, USA","rank":313,"gender_rank":256,"division_rank":102,"pace":"17:38","time":"29:30:32"},{"name":"ROSS CHAPMAN","sex":"M","age":37,"bib":"424","hometown":"Arlington Hts, IL, USA","rank":314,"gender_rank":257,"division_rank":75,"pace":"17:38","time":"29:30:42"},{"name":"Stephen Hinkel","sex":"M","age":43,"bib":"548","hometown":"Lakewood, CO, USA","rank":315,"gender_rank":258,"division_rank":103,"pace":"17:38","time":"29:31:01"},{"name":"Chris Prairie","sex":"M","age":34,"bib":"752","hometown":"Austin, TX, USA","rank":316,"gender_rank":259,"division_rank":76,"pace":"17:39","time":"29:31:39"},{"name":"Sean Newlin","sex":"M","age":34,"bib":"705","hometown":"Oakland, CA, USA","rank":317,"gender_rank":260,"division_rank":77,"pace":"17:39","time":"29:31:39"},{"name":"Cristobal Forno","sex":"M","age":40,"bib":"221","hometown":"Boulder, CO, USA","rank":318,"gender_rank":261,"division_rank":104,"pace":"17:39","time":"29:31:59"},{"name":"Eric Pence","sex":"M","age":56,"bib":"27","hometown":"Eagle, CO, USA","rank":319,"gender_rank":262,"division_rank":44,"pace":"17:39","time":"29:31:59"},{"name":"Philippe Boutros","sex":"M","age":30,"bib":"385","hometown":"Boise, ID, USA","rank":320,"gender_rank":263,"division_rank":78,"pace":"17:39","time":"29:32:00"},{"name":"Wesley Reagan","sex":"M","age":41,"bib":"760","hometown":"Sugar Hill, GA, USA","rank":321,"gender_rank":264,"division_rank":105,"pace":"17:39","time":"29:32:13"},{"name":"Dustin Hoffman","sex":"M","age":41,"bib":"551","hometown":"Spearfish, SD, USA","rank":322,"gender_rank":265,"division_rank":106,"pace":"17:39","time":"29:32:22"},{"name":"Yekaterina Petrova","sex":"F","age":38,"bib":"98","hometown":"Parker, CO, USA","rank":323,"gender_rank":57,"division_rank":27,"pace":"17:39","time":"29:32:45"},{"name":"Kevin Flannery","sex":"M","age":43,"bib":"485","hometown":"Arvada, CO, USA","rank":324,"gender_rank":266,"division_rank":107,"pace":"17:40","time":"29:33:26"},{"name":"Anton Simorov","sex":"M","age":35,"bib":"820","hometown":"Grand Island, NE, USA","rank":325,"gender_rank":267,"division_rank":79,"pace":"17:40","time":"29:33:32"},{"name":"Jules Godino","sex":"M","age":29,"bib":"509","hometown":"Guilford, CT, USA","rank":326,"gender_rank":268,"division_rank":30,"pace":"17:40","time":"29:33:42"},{"name":"Andrew Pollard","sex":"M","age":29,"bib":"751","hometown":"Framingham, MA, USA","rank":327,"gender_rank":269,"division_rank":31,"pace":"17:40","time":"29:34:05"},{"name":"Josh Welch","sex":"M","age":39,"bib":"905","hometown":"Phoenix, AZ, USA","rank":328,"gender_rank":270,"division_rank":80,"pace":"17:40","time":"29:34:13"},{"name":"Michael Robertson","sex":"M","age":30,"bib":"773","hometown":"Gun Barrel City, TX, USA","rank":329,"gender_rank":271,"division_rank":81,"pace":"17:40","time":"29:34:23"},{"name":"Richard Toy","sex":"M","age":43,"bib":"881","hometown":"Austin, TX, USA","rank":330,"gender_rank":272,"division_rank":108,"pace":"17:41","time":"29:34:56"},{"name":"James Hughes","sex":"M","age":50,"bib":"160","hometown":"Boylston, MA, USA","rank":331,"gender_rank":273,"division_rank":45,"pace":"17:41","time":"29:35:26"},{"name":"Hamish MacDonald","sex":"M","age":41,"bib":"635","hometown":"Surry Hills, -, AUS","rank":332,"gender_rank":274,"division_rank":109,"pace":"17:41","time":"29:35:53"},{"name":"Justin Fishburn","sex":"M","age":42,"bib":"270","hometown":"Boise, ID, USA","rank":333,"gender_rank":275,"division_rank":110,"pace":"17:42","time":"29:36:18"},{"name":"Johna Iannitto","sex":"F","age":33,"bib":"51","hometown":"Dillon, CO, USA","rank":334,"gender_rank":58,"division_rank":28,"pace":"17:42","time":"29:37:29"},{"name":"Brett Johnson","sex":"M","age":37,"bib":"572","hometown":"Anchorage, AK, USA","rank":335,"gender_rank":276,"division_rank":82,"pace":"17:42","time":"29:37:40"},{"name":"Frank D Dumont","sex":"M","age":53,"bib":"126","hometown":"Estes Park, CO, USA","rank":336,"gender_rank":277,"division_rank":46,"pace":"17:43","time":"29:38:12"},{"name":"Graham Zimmerman","sex":"M","age":33,"bib":"935","hometown":"Chapel Hill, NC, USA","rank":337,"gender_rank":278,"division_rank":83,"pace":"17:43","time":"29:39:31"},{"name":"Chad Mraz","sex":"M","age":39,"bib":"97","hometown":"Arvada, CO, USA","rank":338,"gender_rank":279,"division_rank":84,"pace":"17:44","time":"29:39:44"},{"name":"Oliver Sybert","sex":"M","age":28,"bib":"863","hometown":"San Diego, CA, USA","rank":339,"gender_rank":280,"division_rank":32,"pace":"17:44","time":"29:40:02"},{"name":"Ryan Cotter","sex":"M","age":35,"bib":"217","hometown":"Denver, CO, USA","rank":340,"gender_rank":281,"division_rank":85,"pace":"17:45","time":"29:42:02"},{"name":"Yumei Guo","sex":"F","age":52,"bib":"521","hometown":"Long Valley, NJ, USA","rank":341,"gender_rank":59,"division_rank":5,"pace":"17:45","time":"29:42:15"},{"name":"Teal Carlock","sex":"M","age":40,"bib":"167","hometown":"Dallas, TX, USA","rank":342,"gender_rank":282,"division_rank":111,"pace":"17:45","time":"29:42:26"},{"name":"Miki McConaha","sex":"F","age":38,"bib":"663","hometown":"Arvada, CO, USA","rank":343,"gender_rank":60,"division_rank":29,"pace":"17:45","time":"29:42:45"},{"name":"Lindsey Sachs","sex":"F","age":41,"bib":"52","hometown":"Nederland, CO, USA","rank":344,"gender_rank":61,"division_rank":20,"pace":"17:45","time":"29:42:49"},{"name":"Evan Weisel","sex":"M","age":51,"bib":"904","hometown":"Alexandria, VA, USA","rank":345,"gender_rank":283,"division_rank":47,"pace":"17:46","time":"29:42:58"},{"name":"Kristopher Simons","sex":"M","age":38,"bib":"108","hometown":"Brighton, CO, USA","rank":346,"gender_rank":284,"division_rank":86,"pace":"17:46","time":"29:43:31"},{"name":"jose sosa","sex":"M","age":41,"bib":"834","hometown":"Chula Vista, CA, USA","rank":347,"gender_rank":285,"division_rank":112,"pace":"17:46","time":"29:44:02"},{"name":"Margaret Montfort","sex":"F","age":62,"bib":"684","hometown":"Flagstaff, AZ, USA","rank":348,"gender_rank":62,"division_rank":1,"pace":"17:46","time":"29:44:06"},{"name":"Sarah Teruel","sex":"F","age":32,"bib":"872","hometown":"Midland, TX, USA","rank":349,"gender_rank":63,"division_rank":30,"pace":"17:46","time":"29:44:27"},{"name":"Mike Niebrzydowski","sex":"M","age":37,"bib":"710","hometown":"Denver, CO, USA","rank":350,"gender_rank":286,"division_rank":87,"pace":"17:47","time":"29:46:02"}]
[{"name":"Stacy Ciarleglio","sex":"F","age":41,"bib":"426","hometown":"Santa Fe, NM, USA","rank":351,"gender_rank":64,"division_rank":21,"pace":"17:48","time":"29:47:03"},{"name":"Christophe Famechon","sex":"M","age":54,"bib":"480","hometown":"Gardanne, -, FRA","rank":352,"gender_rank":287,"division_rank":48,"pace":"17:48","time":"29:47:44"},{"name":"Mark Smith","sex":"M","age":44,"bib":"827","hometown":"Atlanta, GA, USA","rank":353,"gender_rank":288,"division_rank":113,"pace":"17:49","time":"29:48:14"},{"name":"Scott Evenson","sex":"M","age":56,"bib":"475","hometown":"Pittsboro, NC, USA","rank":354,"gender_rank":289,"division_rank":49,"pace":"17:50","time":"29:49:44"},{"name":"Dan Rieland","sex":"M","age":55,"bib":"771","hometown":"Billings, MT, USA","rank":355,"gender_rank":290,"division_rank":50,"pace":"17:50","time":"29:51:05"},{"name":"Jason Kumlien","sex":"M","age":52,"bib":"318","hometown":"Tampa, FL, USA","rank":356,"gender_rank":291,"division_rank":51,"pace":"17:51","time":"29:51:28"},{"name":"Brian Watson","sex":"M","age":47,"bib":"902","hometown":"Rockwall, TX, USA","rank":357,"gender_rank":292,"division_rank":114,"pace":"17:51","time":"29:51:36"},{"name":"Casey Mendrala","sex":"F","age":33,"bib":"677","hometown":"Ludlow, MA, USA","rank":358,"gender_rank":65,"division_rank":31,"pace":"17:51","time":"29:51:59"},{"name":"Rachel Ellerman","sex":"F","age":44,"bib":"914","hometown":"Milwaukee, WI, USA","rank":359,"gender_rank":66,"division_rank":22,"pace":"17:51","time":"29:52:50"},{"name":"Mark Gregware","sex":"M","age":42,"bib":"513","hometown":"Minneapolis, MN, USA","rank":360,"gender_rank":293,"division_rank":115,"pace":"17:52","time":"29:53:16"},{"name":"Mandi Merica","sex":"F","age":35,"bib":"678","hometown":"Morrison, CO, USA","rank":361,"gender_rank":67,"division_rank":32,"pace":"17:52","time":"29:53:19"},{"name":"Mitchell Cohen","sex":"M","age":52,"bib":"322","hometown":"Boulder, CO, USA","rank":362,"gender_rank":294,"division_rank":52,"pace":"17:53","time":"29:54:52"},{"name":"Alexis Knight","sex":"F","age":32,"bib":"591","hometown":"Rifle, CO, USA","rank":363,"gender_rank":68,"division_rank":33,"pace":"17:53","time":"29:54:55"},{"name":"Wade Jarvis","sex":"M","age":60,"bib":"31","hometown":"Cochrane, ALBERTA, CAN","rank":364,"gender_rank":295,"division_rank":5,"pace":"17:53","time":"29:55:09"},{"name":"Mickey Martin","sex":"M","age":33,"bib":"649","hometown":"Evergreen, CO, USA","rank":365,"gender_rank":296,"division_rank":1,"pace":"17:53","time":"29:55:17"},{"name":"Nicholas Charlwood","sex":"M","age":52,"bib":"316","hometown":"Evergreen, CO, USA","rank":366,"gender_rank":297,"division_rank":53,"pace":"18:06","time":"30:17:32"}]
